setup.py
cclient/__init__.py
cclient/example.py
cli2_client.egg-info/PKG-INFO
cli2_client.egg-info/SOURCES.txt
cli2_client.egg-info/dependency_links.txt
cli2_client.egg-info/entry_points.txt
cli2_client.egg-info/requires.txt
cli2_client.egg-info/top_level.txt